odoo/addons/l10n_br_website_sale/README.rst
odoo/addons/l10n_br_website_sale/__init__.py
odoo/addons/l10n_br_website_sale/__manifest__.py
odoo/addons/l10n_br_website_sale/controllers/__init__.py
odoo/addons/l10n_br_website_sale/controllers/main.py
odoo/addons/l10n_br_website_sale/i18n/l10n_br_website_sale.pot
odoo/addons/l10n_br_website_sale/i18n/pt_BR.po
odoo/addons/l10n_br_website_sale/readme/CONFIGURE.rst
odoo/addons/l10n_br_website_sale/readme/CONTRIBUTORS.rst
odoo/addons/l10n_br_website_sale/readme/CREDITS.rst
odoo/addons/l10n_br_website_sale/readme/DESCRIPTION.rst
odoo/addons/l10n_br_website_sale/readme/HISTORY.rst
odoo/addons/l10n_br_website_sale/readme/INSTALL.rst
odoo/addons/l10n_br_website_sale/readme/ROADMAP.rst
odoo/addons/l10n_br_website_sale/readme/USAGE.rst
odoo/addons/l10n_br_website_sale/static/description/icon.png
odoo/addons/l10n_br_website_sale/static/description/index.html
odoo/addons/l10n_br_website_sale/static/src/js/l10n_br_address.js
odoo/addons/l10n_br_website_sale/static/src/js/l10n_br_website_sale_tour.js
odoo/addons/l10n_br_website_sale/templates/portal_templates.xml
odoo/addons/l10n_br_website_sale/tests/__init__.py
odoo/addons/l10n_br_website_sale/tests/test_sale_process.py
odoo/addons/l10n_br_website_sale/views/assets.xml
odoo14_addon_l10n_br_website_sale-14.0.2.1.2.dist-info/METADATA
odoo14_addon_l10n_br_website_sale-14.0.2.1.2.dist-info/WHEEL
odoo14_addon_l10n_br_website_sale-14.0.2.1.2.dist-info/top_level.txt
odoo14_addon_l10n_br_website_sale-14.0.2.1.2.dist-info/RECORD
